vamb/__init__.py
vamb/__main__.py
vamb/_vambtools.cpython-37m-darwin.so
vamb/benchmark.py
vamb/cluster.py
vamb/encode.py
vamb/kernel.npz
vamb/parsebam.py
vamb/parsecontigs.py
vamb/vambtools.py
vamb-3.0.2.data/scripts/concatenate.py
vamb-3.0.2.dist-info/LICENSE
vamb-3.0.2.dist-info/METADATA
vamb-3.0.2.dist-info/WHEEL
vamb-3.0.2.dist-info/entry_points.txt
vamb-3.0.2.dist-info/top_level.txt
vamb-3.0.2.dist-info/RECORD
