Metadata-Version: 2.1
Name: vamb
Version: 3.0.2
Summary: Variational autoencoder for metagenomic binning
Home-page: https://github.com/jakobnissen/vamb
Author: Jakob Nybo Nissen and Simon Rasmussen
Author-email: jakobnybonissen@gmail.com
License: MIT
Platform: UNKNOWN
Classifier: Programming Language :: Python :: 3
Classifier: License :: OSI Approved :: MIT License
Classifier: Operating System :: OS Independent
Requires-Python: >=3.5
Requires-Dist: numpy (>=1.15)
Requires-Dist: torch (>=1.4)
Requires-Dist: pysam (>=0.14)
Requires-Dist: torchvision (>=0.6)
